pyphy/__init__.py
pyphy/prepyphy.py
pyphy/pyphy.py
pyphy/test_pyphy.py
pyphy-1.0.3.dist-info/LICENSE
pyphy-1.0.3.dist-info/METADATA
pyphy-1.0.3.dist-info/WHEEL
pyphy-1.0.3.dist-info/top_level.txt
pyphy-1.0.3.dist-info/RECORD
