Metadata-Version: 2.1
Name: pyphy
Version: 1.0.3
Summary: A python package to interact with NCBI taxonomy
Home-page: https://github.com/dgg32/pyphy
Author: Sixing Huang
Author-email: dgg321982@gmail.com
License: MIT
Project-URL: Bug Tracker, https://github.com/dgg32/pyphy/issues
Keywords: NCBI taxonomy for python
Platform: UNKNOWN
Classifier: Programming Language :: Python :: 3
Classifier: License :: OSI Approved :: MIT License
Classifier: Operating System :: OS Independent
Requires-Python: >=3.6
License-File: LICENSE
